PyTerm/__init__.py
PyTerm/cli_assist.py
PyTerm/config.json
PyTerm/styles.css
PyTerm_Shell-0.1.12.dist-info/METADATA
PyTerm_Shell-0.1.12.dist-info/WHEEL
PyTerm_Shell-0.1.12.dist-info/entry_points.txt
PyTerm_Shell-0.1.12.dist-info/top_level.txt
PyTerm_Shell-0.1.12.dist-info/RECORD
